{
    "/js/front.js": "/js/front.js?id=d2bbf565f0493c8c06fa",
    "/js/admin.js": "/js/admin.js?id=4be75b2d923e55bb450c",
    "/js/manifest.js": "/js/manifest.js?id=10232ca82de81dd79879",
    "/css/admin.css": "/css/admin.css?id=f6f5dacd9401a89b224e",
    "/css/front.css": "/css/front.css?id=5c23e60a9ce20fddff5b",
    "/js/vendor.js": "/js/vendor.js?id=6f5c3c575bebf668e3f8",
    "/js/amChartMap.js": "/js/amChartMap.js?id=3b16569289e89cc376ca",
    "/js/amChartMap.min.js": "/js/amChartMap.min.js?id=3b16569289e89cc376ca",
    "/js/amChartTranscript.js": "/js/amChartTranscript.js?id=a61b82f64cc689655c1d",
    "/js/amChartTranscript.min.js": "/js/amChartTranscript.min.js?id=a61b82f64cc689655c1d",
    "/js/amChartStat.js": "/js/amChartStat.js?id=35732e8e1d6fd8ced9cc",
    "/js/amChartStat.min.js": "/js/amChartStat.min.js?id=35732e8e1d6fd8ced9cc",
    "/js/amChartEventRate.js": "/js/amChartEventRate.js?id=11de3e39e4ffd534d3ef",
    "/js/amChartEventRate.min.js": "/js/amChartEventRate.min.js?id=11de3e39e4ffd534d3ef",
    "/js/amChartBingo.js": "/js/amChartBingo.js?id=98540534c32c934a324c",
    "/js/amChartBingo.min.js": "/js/amChartBingo.min.js?id=98540534c32c934a324c",
    "/js/jquery.form.min.js": "/js/jquery.form.min.js?id=f448c593c242d134e973",
    "/js/expertReview.js": "/js/expertReview.js?id=331668b914669c01c1ac",
    "/js/expertReview.min.js": "/js/expertReview.min.js?id=331668b914669c01c1ac"
}
